{
	"x": 384,
	"y": 64,
	"width": 128,
	"height": 192,
	"iid": "4272e920-02f0-11ed-b717-efc98a1b3e1b",
	"layers": [],
	"entities": {
		"RedPlayer": [
			{
				"id": "RedPlayer",
				"iid": "57f643f0-02f0-11ed-b717-ff3147bf755e",
				"layer": "Entities",
				"x": 48,
				"y": 32,
				"width": 16,
				"height": 16,
				"color": 16711680,
				"customFields" : {}
			}
		],
		"GreenTrap": [
			{
				"id": "GreenTrap",
				"iid": "9b38e4b0-02f0-11ed-b717-6b2d7e098df0",
				"layer": "Entities",
				"x": 80,
				"y": 48,
				"width": 16,
				"height": 16,
				"color": 65280,
				"customFields" : {}
			},
			{
				"id": "GreenTrap",
				"iid": "9b59da30-02f0-11ed-b717-31abcfabe342",
				"layer": "Entities",
				"x": 80,
				"y": 64,
				"width": 16,
				"height": 16,
				"color": 65280,
				"customFields" : {}
			},
			{
				"id": "GreenTrap",
				"iid": "9b8f4210-02f0-11ed-b717-8d213951d69e",
				"layer": "Entities",
				"x": 64,
				"y": 64,
				"width": 16,
				"height": 16,
				"color": 65280,
				"customFields" : {}
			},
			{
				"id": "GreenTrap",
				"iid": "9bf508c0-02f0-11ed-b717-51f2721f4877",
				"layer": "Entities",
				"x": 64,
				"y": 80,
				"width": 16,
				"height": 16,
				"color": 65280,
				"customFields" : {}
			},
			{
				"id": "GreenTrap",
				"iid": "9c2a70a0-02f0-11ed-b717-616d8b3e7f00",
				"layer": "Entities",
				"x": 48,
				"y": 80,
				"width": 16,
				"height": 16,
				"color": 65280,
				"customFields" : {}
			},
			{
				"id": "GreenTrap",
				"iid": "9ce18ba0-02f0-11ed-b717-abde5f3269bd",
				"layer": "Entities",
				"x": 32,
				"y": 80,
				"width": 16,
				"height": 16,
				"color": 65280,
				"customFields" : {}
			},
			{
				"id": "GreenTrap",
				"iid": "a77add00-02f0-11ed-b717-73e4d4a44a54",
				"layer": "Entities",
				"x": 16,
				"y": 96,
				"width": 16,
				"height": 16,
				"color": 65280,
				"customFields" : {}
			},
			{
				"id": "GreenTrap",
				"iid": "a7ff2830-02f0-11ed-b717-c5c80cc29c19",
				"layer": "Entities",
				"x": 16,
				"y": 112,
				"width": 16,
				"height": 16,
				"color": 65280,
				"customFields" : {}
			},
			{
				"id": "GreenTrap",
				"iid": "a86515f0-02f0-11ed-b717-0b245a1bf6cc",
				"layer": "Entities",
				"x": 32,
				"y": 128,
				"width": 16,
				"height": 16,
				"color": 65280,
				"customFields" : {}
			},
			{
				"id": "GreenTrap",
				"iid": "a8ee6a30-02f0-11ed-b717-91cce0851d4d",
				"layer": "Entities",
				"x": 48,
				"y": 128,
				"width": 16,
				"height": 16,
				"color": 65280,
				"customFields" : {}
			},
			{
				"id": "GreenTrap",
				"iid": "a932ed40-02f0-11ed-b717-b5b657e49b2b",
				"layer": "Entities",
				"x": 64,
				"y": 128,
				"width": 16,
				"height": 16,
				"color": 65280,
				"customFields" : {}
			},
			{
				"id": "GreenTrap",
				"iid": "aa2c1a50-02f0-11ed-b717-f1b3f6572fa4",
				"layer": "Entities",
				"x": 80,
				"y": 96,
				"width": 16,
				"height": 16,
				"color": 65280,
				"customFields" : {}
			},
			{
				"id": "GreenTrap",
				"iid": "ab533530-02f0-11ed-b717-73f966ca7a44",
				"layer": "Entities",
				"x": 112,
				"y": 64,
				"width": 16,
				"height": 16,
				"color": 65280,
				"customFields" : {}
			},
			{
				"id": "GreenTrap",
				"iid": "ac9db690-02f0-11ed-b717-8f85edff26ce",
				"layer": "Entities",
				"x": 96,
				"y": 64,
				"width": 16,
				"height": 16,
				"color": 65280,
				"customFields" : {}
			},
			{
				"id": "GreenTrap",
				"iid": "afe25a40-02f0-11ed-b717-cb7594091cad",
				"layer": "Entities",
				"x": 96,
				"y": 112,
				"width": 16,
				"height": 16,
				"color": 65280,
				"customFields" : {}
			}
		],
		"WhiteGoal": [
			{
				"id": "WhiteGoal",
				"iid": "3f79ff00-02f0-11ed-b717-8f78d54d92f4",
				"layer": "Entities",
				"x": 48,
				"y": 112,
				"width": 16,
				"height": 16,
				"color": 16777215,
				"customFields" : {}
			}
		]
	}
}